cibo/__init__.py
cibo/app.py
cibo/args.py
cibo/blueprint.py
cibo/context.py
cibo/cors.py
cibo/decorators.py
cibo/handler.py
cibo/types.py
cibo/ui_templates.py
cibo/utils.py
cibo-0.0.1.dev0.dist-info/LICENSE
cibo-0.0.1.dev0.dist-info/METADATA
cibo-0.0.1.dev0.dist-info/WHEEL
cibo-0.0.1.dev0.dist-info/top_level.txt
cibo-0.0.1.dev0.dist-info/RECORD
