Metadata-Version: 2.1
Name: cibo
Version: 0.0.1.dev0
Summary: A web framework that is composed of flask, pydantic, and openapi 3.
Home-page: https://github.com/yangfan9702/cibo
Author: yangfan
Author-email: yangfan9702@outlook.com
Maintainer: yangfan
Maintainer-email: yangfan9702@outlook.com
License: MIT License
Project-URL: Source Code, https://github.com/yangfan9702/cibo
Platform: UNKNOWN
Requires-Python: >=3.7
License-File: LICENSE
Requires-Dist: Flask (==1.1.1)
Requires-Dist: pydantic (==1.6.2)
Requires-Dist: apispec (==5.0.0)
Requires-Dist: typing-extensions (==3.10.0.2)
